sodasql/dialects/athena_dialect.py
sodasql/scan/aws_credentials.py
soda_sql_athena-2.2.2.dist-info/METADATA
soda_sql_athena-2.2.2.dist-info/WHEEL
soda_sql_athena-2.2.2.dist-info/top_level.txt
soda_sql_athena-2.2.2.dist-info/RECORD
